henryobj/__init__.py
henryobj/base.py
henryobj/config.py
henryobj/gpt.py
henryobj/oai.py
henryobj/web.py
henryobj-0.3.2.dist-info/METADATA
henryobj-0.3.2.dist-info/WHEEL
henryobj-0.3.2.dist-info/top_level.txt
henryobj-0.3.2.dist-info/RECORD
