Metadata-Version: 2.1
Name: henryobj
Version: 0.3.2
Home-page: https://github.com/HenryObj/mypip
Requires-Dist: openai >=1.33.0
Requires-Dist: tiktoken >=0.5.2
Requires-Dist: requests >=2.31.0
Requires-Dist: bs4
Requires-Dist: pathspec
